VytalGazeClient-0.1.7.data/data/vytalgaze_client/config/config.json
vytalgaze_client/__init__.py
vytalgaze_client/client.py
VytalGazeClient-0.1.7.dist-info/LICENSE
VytalGazeClient-0.1.7.dist-info/METADATA
VytalGazeClient-0.1.7.dist-info/WHEEL
VytalGazeClient-0.1.7.dist-info/top_level.txt
VytalGazeClient-0.1.7.dist-info/RECORD
