Metadata-Version: 2.1
Name: VytalGazeClient
Version: 0.1.7
Summary: Client for Vytal Gaze API.
Home-page: https://github.com/vytal-ai/vytalgaze_client
Author: Vytal.ai
Author-email: sritanmotati@gmail.com
License: MIT
Keywords: starter,package,template
Classifier: Development Status :: 3 - Alpha
Classifier: License :: OSI Approved :: MIT License
Classifier: Natural Language :: English
Classifier: Operating System :: OS Independent
Classifier: Programming Language :: Python
Classifier: Programming Language :: Python :: 3
Classifier: Programming Language :: Python :: 3 :: Only
Classifier: Programming Language :: Python :: 3.8
Classifier: Programming Language :: Python :: 3.9
Classifier: Programming Language :: Python :: 3.10
Classifier: Programming Language :: Python :: 3.11
Classifier: Intended Audience :: Developers
Classifier: Intended Audience :: Science/Research
Classifier: Intended Audience :: Information Technology
Classifier: Topic :: Software Development
Classifier: Topic :: Software Development :: Libraries
Requires-Python: >=3.8
License-File: LICENSE
Requires-Dist: requests
Requires-Dist: numpy
Requires-Dist: torch
